prompt_sensitivity_index/__init__.py
prompt_sensitivity_index/posix.py
prompt_sensitivity_index/models/__init__.py
prompt_sensitivity_index/models/base.py
prompt_sensitivity_index/models/hf_model.py
prompt_sensitivity_index-0.0.1.dist-info/LICENSE
prompt_sensitivity_index-0.0.1.dist-info/METADATA
prompt_sensitivity_index-0.0.1.dist-info/WHEEL
prompt_sensitivity_index-0.0.1.dist-info/top_level.txt
prompt_sensitivity_index-0.0.1.dist-info/RECORD
