Metadata-Version: 2.1
Name: prompt-sensitivity-index
Version: 0.0.1
Summary: A Prompt Sensitivity Index for Language Models
Author-email: H S V N S Kowndinya Renduchintala <rharisrikowndinya333@gmail.com>, Anwoy Chatterjee <anwoychatterjee@gmail.com>, Sumit Bhatia <sumit.summit@gmail.com>, Tanmoy Chakraborty <chak.tanmoy.iit@gmail.com>
Project-URL: Homepage, https://github.com/kowndinya-renduchintala/POSIX
Project-URL: Issues, https://github.com/kowndinya-renduchintala/POSIX/issues
Classifier: Programming Language :: Python :: 3
Classifier: License :: OSI Approved :: MIT License
Classifier: Operating System :: OS Independent
Requires-Python: >=3.8
License-File: LICENSE
Requires-Dist: torch
Requires-Dist: transformers
